{
  "endorser": "NQF",
  "id": "1406",
  "properties": "NQF_Retooled_Measure_0575.xlsx.json",
  "name": "Risky Behavior Assessment or Counseling by Age 13 Years",
  "description": "Percentage of children with documentation of a risk assessment or counseling for risky behaviors by the age of 13 years. Four rates are reported: Risk Assessment or Counseling for Alcohol Use, Risk Assessment or Counseling for Tobacco Use, Risk Assessment or Counseling for Other Substance Abuse, Risk Assessment or Counseling for Sexual Activity",
  "category": "Behavioral Health",
  "steward": "NCQA",
  "parameters": {
    "effective_date": {
      "description": "Effective end date for measure",
      "type": "number",
      "format": "utc-sec" 
    } 
  },
  "patient": {
    "birthdate": {
      "description": "Date of birth",
      "critical": true,
      "type": "number",
      "format": "utc-sec",
      "codes": [
        {
          "set": "HL7",
          "version": "3.0",
          "values": [
            "00110"
          ] 
        } 
      ] 
    } 
  },
  "population": {
    "and":[
    {
      "category": "Patient Characteristic",
      "title": "age <= 12 before start of Measurement Period" 
    },
    {"or":
      [
        {
        "category": "Encounter",
        "title": "Office Visit performed <= 12 years old" 
        },
        {
          "category": "Encounter",
          "title": "Face-to-Face Interaction performed <= 12 years old" 
        },
        {
          "category": "Encounter",
          "title": "Outpatient consultation performed <= 12 years old" 
        }
       ]
      }
    ]
  },
  "denominator": {
        "category": "Patient Characteristic",
        "title": "In Initial Patient Population" 
      }
  ,
  "numerator": {
    "or":[
    {"and":
       [
        {
        "category": "Intervention, ordered",
          "title": "Occurrence A: Counseling for Substance Abuse when 11 years old <= age <=13 years old "
        },
        {
        "category": "Intervention, performed",
          "title": "Occurrence A: Counseling for Substance Abuse when 11 years old <= age <=13 years old "
        }
       ]
      },
      {"and":
       [
        {
        "category": "Intervention, ordered",
          "title": "Occurrence A: Counseling for Alcohol Abuse when 11 years old <= age <=13 years old "
        },
        {
        "category": "Intervention, performed",
          "title": "Occurrence A: Counseling for Alcohol Abuse when 11 years old <= age <=13 years old "
        }
       ]
      },
      {"and":
       [
        {
        "category": "Intervention, ordered",
          "title": "Occurrence A:Counseling for Sexual Activity when 11 years old <= age <=13 years old "
        },
        {
        "category": "Intervention, performed",
          "title": "Occurrence A:Counseling for Sexual Activity when 11 years old <= age <=13 years old "
        }
       ]
      },
      {"and":
       [
        {
        "category": "Intervention, ordered",
          "title": "Occurrence A: Counseling for Tobacco Abuse when 11 years old <= age <=13 years old "
        },
        {
        "category": "Intervention, performed",
          "title": "Occurrence A: Counseling for Tobacco Abuse when 11 years old <= age <=13 years old "
        }
       ]
      }
    ]
  }
}